draftail_helpers/__init__.py
draftail_helpers/apps.py
draftail_helpers/feature_registry.py
draftail_helpers/editors/__init__.py
draftail_helpers/editors/draftail/__init__.py
draftail_helpers/editors/draftail/control_feature.py
draftail_helpers/editors/draftail/plugin_feature.py
draftail_helpers/static/draftail_helpers/css/draftail_helpers.css
draftail_helpers/static/draftail_helpers/js/draftail_helpers.js
draftail_helpers/static/wagtailadmin/js/draftail_control_feature.js
draftail_helpers/static/wagtailadmin/js/draftail_plugin_support.js
draftail_helpers-4.1.0.dist-info/AUTHORS.txt
draftail_helpers-4.1.0.dist-info/LICENSE.txt
draftail_helpers-4.1.0.dist-info/METADATA
draftail_helpers-4.1.0.dist-info/WHEEL
draftail_helpers-4.1.0.dist-info/top_level.txt
draftail_helpers-4.1.0.dist-info/zip-safe
draftail_helpers-4.1.0.dist-info/RECORD
